MANIFEST.in
README.rst
setup.cfg
setup.py
Notebook/Test_library.ipynb
pdsimage/PDS_Extractor.py
pdsimage/Structure.py
pdsimage/__init__.py
pdsimage.egg-info/PKG-INFO
pdsimage.egg-info/SOURCES.txt
pdsimage.egg-info/dependency_links.txt
pdsimage.egg-info/not-zip-safe
pdsimage.egg-info/requires.txt
pdsimage.egg-info/top_level.txt
pdsimage/Table/Data_Crater.csv
pdsimage/Table/Data_Dome.csv