Metadata-Version: 1.1
Name: pdsimage
Version: 1.1.2
Summary: Package for creating images from NASA PDS files
Home-page: https://github.com/cthorey/pdsimage
Author: Thorey Clement
Author-email: clement.thorey@gmail.com
License: MIT
Download-URL: https://github.com/cthorey/pdsimage/tarball/1.1.2
Keywords: PDS,LOLA,WAC,crater,dome,FFC,floor-fractured craters
Platform: UNKNOWN
